[
    {
        "name" : "node",
        "pm" : "snap",
        "type" : "server",
        "arguments" : ["--classic", "--channel=12/stable"]
    },
    {
        "name" : "code",
        "pm" : "snap",
        "type" : "workstation",
        "arguments" : ["--classic"]
    },
    {
        "name" : "postman",
        "pm" : "snap",
        "type" : "workstation",
        "arguments" : []
    },
    {
        "name" : "cmake",
        "pm" : "snap",
        "type" : "server",
        "arguments" : ["--classic"]
    },
    {
        "name" : "clion",
        "pm" : "snap",
        "type" : "workstation",
        "arguments" : ["--classic"]
    },
    {
        "name" : "datagrip",
        "pm" : "snap",
        "type" : "workstation",
        "arguments" : ["--classic"]
    },
    {
        "name" : "intellij-idea-ultimate",
        "pm" : "snap",
        "type" : "workstation",
        "arguments" : ["--classic"]
    },
    {
        "name" : "webstorm",
        "pm" : "snap",
        "type" : "workstation",
        "arguments" : ["--classic"]
    },
    {
        "name" : "pycharm-professional",
        "pm" : "snap",
        "type" : "workstation",
        "arguments" : ["--classic"]
    },
    {
        "name" : "android-studio",
        "pm" : "snap",
        "type" : "workstation",
        "arguments" : ["--classic"]
    },
    {
        "name" : "tldr",
        "pm" : "snap",
        "type" : "server",
        "arguments" : []
    },
    {
        "name" : "default-jdk",
        "pm" : "apt",
        "type" : "server",
        "arguments" : ["-y", "-qq"]
    },
    {
        "name" : "openjdk-8-jdk",
        "pm" : "apt",
        "type" : "server",
        "arguments" : ["-y", "-qq"]
    },
    {
        "name" : "openjdk-11-jdk",
        "pm" : "apt",
        "type" : "server",
        "arguments" : ["-y", "-qq"]
    },
    {
        "name" : "openjdk-13-jdk",
        "pm" : "apt",
        "type" : "server",
        "arguments" : ["-y", "-qq"]
    },
    {
        "name" : "neovim",
        "pm" : "apt",
        "type" : "server",
        "arguments" : ["-y", "-qq"]
    },
    {
        "name" : "python3-pip",
        "pm" : "apt",
        "type" : "server",
        "arguments" : ["-y", "-qq"]
    },
    {
        "name" : "python3-dev",
        "pm" : "apt",
        "type" : "server",
        "arguments" : ["-y", "-qq"]
    },
    {
        "name" : "build-essential",
        "pm" : "apt",
        "type" : "server",
        "arguments" : ["-y", "-qq"]
    },
    {
        "name" : "git",
        "pm" : "apt",
        "type" : "server",
        "arguments" : ["-y", "-qq"]
    },
    {
        "name" : "curl",
        "pm" : "apt",
        "type" : "server",
        "arguments" : ["-y" , "-qq"]
    },
    {
        "name" : "gnome-tweaks",
        "pm" : "apt",
        "type" : "workstation",
        "arguments" : ["-y", "-qq"]
    },
    {
        "name" : "gnome-shell-extensions",
        "pm" : "apt",
        "type" : "workstation",
        "arguments" : ["-y", "-qq"]
    },
    {
        "name" : "dash-to-dock",
        "pm" : "apt",
        "type" : "workstation",
        "arguments" : ["-y", "-qq"]
    }

]
